README.md
setup.py
distributions/Binomialdistribution.py
distributions/Gaussiandistribution.py
distributions/Generaldistribution.py
distributions/__init__.py
lemarc58_distributions_udacity.egg-info/PKG-INFO
lemarc58_distributions_udacity.egg-info/SOURCES.txt
lemarc58_distributions_udacity.egg-info/dependency_links.txt
lemarc58_distributions_udacity.egg-info/not-zip-safe
lemarc58_distributions_udacity.egg-info/top_level.txt